hqlite8/__init__.py
hqlite8/classes.py
hqlite8/enums.py
hqlite8/private_classes.py
hqlite8-1.0.0.dist-info/METADATA
hqlite8-1.0.0.dist-info/WHEEL
hqlite8-1.0.0.dist-info/top_level.txt
hqlite8-1.0.0.dist-info/RECORD
