Metadata-Version: 2.1
Name: hqlite8
Version: 1.0.0
Summary: epic sqlite3 library wrapper im working on (not done - you probably shouldn't use this yet)
Home-page: UNKNOWN
Author: IAmThe2ndHuman
License: MIT
Platform: UNKNOWN
Classifier: Programming Language :: Python :: 3
Classifier: License :: OSI Approved :: MIT License
Requires-Python: >=3.7
